src/stairlight/__init__.py
src/stairlight/__main__.py
src/stairlight/cli.py
src/stairlight/configurator.py
src/stairlight/map.py
src/stairlight/py.typed
src/stairlight/query.py
src/stairlight/source/__init__.py
src/stairlight/source/config.py
src/stairlight/source/config_key.py
src/stairlight/source/controller.py
src/stairlight/source/dbt/__init__.py
src/stairlight/source/dbt/config.py
src/stairlight/source/dbt/template.py
src/stairlight/source/file/__init__.py
src/stairlight/source/file/config.py
src/stairlight/source/file/template.py
src/stairlight/source/gcs/__init__.py
src/stairlight/source/gcs/config.py
src/stairlight/source/gcs/map.py
src/stairlight/source/gcs/template.py
src/stairlight/source/redash/__init__.py
src/stairlight/source/redash/config.py
src/stairlight/source/redash/sql/redash_queries.sql
src/stairlight/source/redash/template.py
src/stairlight/source/s3/__init__.py
src/stairlight/source/s3/config.py
src/stairlight/source/s3/map.py
src/stairlight/source/s3/template.py
src/stairlight/source/template.py
src/stairlight/stairlight.py
src/stairlight/util.py
stairlight-0.9.2.dist-info/LICENSE
stairlight-0.9.2.dist-info/METADATA
stairlight-0.9.2.dist-info/WHEEL
stairlight-0.9.2.dist-info/entry_points.txt
stairlight-0.9.2.dist-info/RECORD
