Metadata-Version: 2.1
Name: stairlight
Version: 0.9.2
Summary: Data lineage tool
License: MIT
Author: tosh2230
Author-email: rev.to12@gmail.com
Requires-Python: >=3.8,<4
Classifier: License :: OSI Approved :: MIT License
Classifier: Programming Language :: Python :: 3
Classifier: Programming Language :: Python :: 3.8
Classifier: Programming Language :: Python :: 3.9
Classifier: Programming Language :: Python :: 3.10
Classifier: Programming Language :: Python :: 3.11
Provides-Extra: dbt-bigquery
Provides-Extra: gcs
Provides-Extra: redash
Provides-Extra: s3
Requires-Dist: Jinja2 (>=2.10.3)
Requires-Dist: PyYAML (!=6.0.0,!=5.4.0,!=5.4.1)
Requires-Dist: SQLAlchemy (>=2.0) ; extra == "redash"
Requires-Dist: boto3 (>=1.24.14) ; extra == "s3"
Requires-Dist: boto3-stubs[s3] (>=1.24.17) ; extra == "s3"
Requires-Dist: cmake (>=3) ; extra == "dbt-bigquery"
Requires-Dist: dbt-adapters (>=1.1.1,<1.2.0) ; extra == "dbt-bigquery"
Requires-Dist: dbt-bigquery (>=1.8) ; extra == "dbt-bigquery"
Requires-Dist: dbt-core (>=1.8) ; extra == "dbt-bigquery"
Requires-Dist: google-cloud-bigquery (>=3.0) ; extra == "dbt-bigquery"
Requires-Dist: google-cloud-storage (>=2.0) ; extra == "gcs"
Requires-Dist: networkx (>=2.3,<2.8.1) ; extra == "dbt-bigquery"
Requires-Dist: protobuf (>=3.20.2) ; extra == "dbt-bigquery" or extra == "gcs"
Requires-Dist: psycopg2 (>=2.9.3) ; extra == "redash"
Requires-Dist: rsa (>=4.7) ; extra == "dbt-bigquery" or extra == "gcs"
